serious_django_permissions/__init__.py
serious_django_permissions/groups.py
serious_django_permissions/helpers.py
serious_django_permissions/models.py
serious_django_permissions/permissions.py
serious_django_permissions/management/__init__.py
serious_django_permissions/management/commands/__init__.py
serious_django_permissions/management/commands/create_groups.py
serious_django_permissions/management/commands/create_permissions.py
serious_django_permissions/migrations/0001_initial.py
serious_django_permissions/migrations/__init__.py
serious_django_permissions-0.17.dist-info/LICENSE
serious_django_permissions-0.17.dist-info/METADATA
serious_django_permissions-0.17.dist-info/WHEEL
serious_django_permissions-0.17.dist-info/top_level.txt
serious_django_permissions-0.17.dist-info/RECORD
